pypimaker/__init__.py
pypimaker/__main__.py
pypimaker/files.py
pypimaker/reset.py
pypimaker/strings.py
pypimaker/upload.py
pypimaker/ui/AuthorInfoSelector.py
pypimaker/ui/DialogWindow.py
pypimaker/ui/OptionSelector.py
pypimaker/ui/__init__.py
pypimaker/ui/navigation.py
tests/__init__.py
tests/test_files.py
tests/test_upload.py
tests/ui/__init__.py
tests/ui/test_navigation.py
pypimaker-1.0.5.dist-info/LICENSE
pypimaker-1.0.5.dist-info/METADATA
pypimaker-1.0.5.dist-info/WHEEL
pypimaker-1.0.5.dist-info/entry_points.txt
pypimaker-1.0.5.dist-info/top_level.txt
pypimaker-1.0.5.dist-info/RECORD
