Metadata-Version: 2.1
Name: pypimaker
Version: 1.0.5
Summary: Software designed for simplifying PyPI Python package setups
Home-page: https://github.com/bdavis222/pypimaker
Author: Brian Davis
Project-URL: Bug Reports, https://github.com/bdavis222/pypimaker/issues
Project-URL: Funding, https://www.paypal.com/donate/?business=UA5NL9MJSFMVY
Project-URL: Source, https://github.com/bdavis222/
Classifier: Intended Audience :: Developers
Classifier: License :: OSI Approved :: MIT License
Classifier: Programming Language :: Python :: 3
Classifier: Operating System :: Unix
Classifier: Operating System :: MacOS :: MacOS X
Classifier: Operating System :: Microsoft :: Windows
Requires-Python: >=3.7, <4
License-File: LICENSE
